social_signals/__init__.py
social_signals/common/__init__.py
social_signals/common/errors.py
social_signals/common/validators.py
social_signals/gdelt/__init__.py
social_signals/gdelt/source.py
social_signals/utils/__init__.py
social_signals/utils/helpers.py
social_signals/wikipedia/__init__.py
social_signals/wikipedia/source.py
social_signals/x/__init__.py
social_signals/x/source.py
social_signals-0.0.3.dist-info/LICENSE
social_signals-0.0.3.dist-info/METADATA
social_signals-0.0.3.dist-info/WHEEL
social_signals-0.0.3.dist-info/RECORD
