Metadata-Version: 2.1
Name: social-signals
Version: 0.0.3
Summary: A package for harvesting social signal feeds.
Author: Olivier Dupuis
Author-email: odupuis@lantrns.co
Requires-Python: >=3.9,<4.0
Classifier: Programming Language :: Python :: 3
Classifier: Programming Language :: Python :: 3.9
Classifier: Programming Language :: Python :: 3.10
Classifier: Programming Language :: Python :: 3.11
Requires-Dist: db-dtypes (>=1.1.1,<2.0.0)
Requires-Dist: google-cloud-bigquery (>=3.13.0,<4.0.0)
Requires-Dist: numpy (>=1.26.0,<2.0.0) ; python_version >= "3.9" and python_version < "3.13"
Requires-Dist: pandas (>=1.5.3,<2.0.0)
Requires-Dist: requests (>=2.31.0,<3.0.0)
Requires-Dist: wikipedia (>=1.4.0,<2.0.0)
